okie/__init__.py
okie/_builders/__init__.py
okie/_builders/_full.py
okie/_builders/base.py
okie/_builders/form_data.py
okie/_builders/form_urlencoded.py
okie/_builders/multipart.py
okie/_builders/utils.py
okie/client.py
okie/ctrl/__init__.py
okie/ctrl/asyncio.py
okie/enums/__init__.py
okie/enums/_named.py
okie/enums/http_request.py
okie/response.py
okie/types.py
okie-0.2.1.dist-info/LICENSE
okie-0.2.1.dist-info/WHEEL
okie-0.2.1.dist-info/METADATA
okie-0.2.1.dist-info/RECORD
